django_smorest/__init__.py
django_smorest/arguments.py
django_smorest/blueprint.py
django_smorest/response.py
django_smorest/spec.py
django_smorest/utils.py
django_smorest/view.py
django_smorest/templates/redoc.html
django_smorest/templates/swagger_ui.html
django_smorest-0.1.3.dist-info/METADATA
django_smorest-0.1.3.dist-info/WHEEL
django_smorest-0.1.3.dist-info/top_level.txt
django_smorest-0.1.3.dist-info/RECORD
