Metadata-Version: 2.1
Name: django-smorest
Version: 0.1.3
Summary: Use flask-smorest for django project.
Home-page: UNKNOWN
Author: UNKNOWN
Author-email: vazgen@hilearn.io
License: UNKNOWN
Platform: UNKNOWN
Classifier: Programming Language :: Python :: 3
Classifier: Development Status :: 3 - Alpha
Requires-Dist: flask (==1.1.1)
Requires-Dist: flask-smorest (==0.18.2)
Requires-Dist: django (==2.2.10)
Requires-Dist: djangorestframework (==3.11.0)
Requires-Dist: webargs (==5.5.3)
